sliceline/__init__.py
sliceline/slicefinder.py
sliceline/validation.py
sliceline-0.2.20.dist-info/LICENSE
sliceline-0.2.20.dist-info/METADATA
sliceline-0.2.20.dist-info/WHEEL
sliceline-0.2.20.dist-info/RECORD
